nameparser/__init__.py
nameparser/parser.py
nameparser/util.py
nameparser/config/__init__.py
nameparser/config/capitalization.py
nameparser/config/conjunctions.py
nameparser/config/prefixes.py
nameparser/config/regexes.py
nameparser/config/suffixes.py
nameparser/config/titles.py
nameparser-1.1.0.dist-info/AUTHORS
nameparser-1.1.0.dist-info/LICENSE
nameparser-1.1.0.dist-info/METADATA
nameparser-1.1.0.dist-info/WHEEL
nameparser-1.1.0.dist-info/top_level.txt
nameparser-1.1.0.dist-info/RECORD
