Metadata-Version: 2.1
Name: nameparser
Version: 1.1.0
Summary: A simple Python module for parsing human names into their individual components.
Home-page: https://github.com/derek73/python-nameparser
Author: Derek Gulbranson
Author-email: derek73@gmail.com
License: LGPL
Keywords: names,parser
Platform: UNKNOWN
Classifier: Intended Audience :: Developers
Classifier: Operating System :: OS Independent
Classifier: License :: OSI Approved :: GNU Library or Lesser General Public License (LGPL)
Classifier: Programming Language :: Python
Classifier: Programming Language :: Python :: 2
Classifier: Programming Language :: Python :: 3
Classifier: Development Status :: 5 - Production/Stable
Classifier: Natural Language :: English
Classifier: Topic :: Software Development :: Libraries :: Python Modules
Classifier: Topic :: Text Processing :: Linguistic
License-File: LICENSE
License-File: AUTHORS
